{
    "unown": {
        "id": 201,
        "name": "unown",
        "height": 5,
        "weight": 50,
        "xp": 118,
        "image_url": "https://pokeres.bastionbot.org/images/pokemon/201.png",
        "abilities": [
            {
                "name": "levitate",
                "is_hidden": false
            }
        ],
        "stats": [
            {
                "name": "hp",
                "base_stat": 48
            },
            {
                "name": "attack",
                "base_stat": 72
            },
            {
                "name": "defense",
                "base_stat": 48
            },
            {
                "name": "special-attack",
                "base_stat": 72
            },
            {
                "name": "special-defense",
                "base_stat": 48
            },
            {
                "name": "speed",
                "base_stat": 48
            }
        ],
        "types": [
            {
                "name": "psychic"
            }
        ]
    },
    "wobbuffet": {
        "id": 202,
        "name": "wobbuffet",
        "height": 13,
        "weight": 285,
        "xp": 142,
        "image_url": "https://pokeres.bastionbot.org/images/pokemon/202.png",
        "abilities": [
            {
                "name": "shadow-tag",
                "is_hidden": false
            },
            {
                "name": "telepathy",
                "is_hidden": true
            }
        ],
        "stats": [
            {
                "name": "hp",
                "base_stat": 190
            },
            {
                "name": "attack",
                "base_stat": 33
            },
            {
                "name": "defense",
                "base_stat": 58
            },
            {
                "name": "special-attack",
                "base_stat": 33
            },
            {
                "name": "special-defense",
                "base_stat": 58
            },
            {
                "name": "speed",
                "base_stat": 33
            }
        ],
        "types": [
            {
                "name": "psychic"
            }
        ]
    },
    "girafarig": {
        "id": 203,
        "name": "girafarig",
        "height": 15,
        "weight": 415,
        "xp": 159,
        "image_url": "https://pokeres.bastionbot.org/images/pokemon/203.png",
        "abilities": [
            {
                "name": "inner-focus",
                "is_hidden": false
            },
            {
                "name": "early-bird",
                "is_hidden": false
            },
            {
                "name": "sap-sipper",
                "is_hidden": true
            }
        ],
        "stats": [
            {
                "name": "hp",
                "base_stat": 70
            },
            {
                "name": "attack",
                "base_stat": 80
            },
            {
                "name": "defense",
                "base_stat": 65
            },
            {
                "name": "special-attack",
                "base_stat": 90
            },
            {
                "name": "special-defense",
                "base_stat": 65
            },
            {
                "name": "speed",
                "base_stat": 85
            }
        ],
        "types": [
            {
                "name": "normal"
            },
            {
                "name": "psychic"
            }
        ]
    },
    "pineco": {
        "id": 204,
        "name": "pineco",
        "height": 6,
        "weight": 72,
        "xp": 58,
        "image_url": "https://pokeres.bastionbot.org/images/pokemon/204.png",
        "abilities": [
            {
                "name": "sturdy",
                "is_hidden": false
            },
            {
                "name": "overcoat",
                "is_hidden": true
            }
        ],
        "stats": [
            {
                "name": "hp",
                "base_stat": 50
            },
            {
                "name": "attack",
                "base_stat": 65
            },
            {
                "name": "defense",
                "base_stat": 90
            },
            {
                "name": "special-attack",
                "base_stat": 35
            },
            {
                "name": "special-defense",
                "base_stat": 35
            },
            {
                "name": "speed",
                "base_stat": 15
            }
        ],
        "types": [
            {
                "name": "bug"
            }
        ]
    },
    "forretress": {
        "id": 205,
        "name": "forretress",
        "height": 12,
        "weight": 1258,
        "xp": 163,
        "image_url": "https://pokeres.bastionbot.org/images/pokemon/205.png",
        "abilities": [
            {
                "name": "sturdy",
                "is_hidden": false
            },
            {
                "name": "overcoat",
                "is_hidden": true
            }
        ],
        "stats": [
            {
                "name": "hp",
                "base_stat": 75
            },
            {
                "name": "attack",
                "base_stat": 90
            },
            {
                "name": "defense",
                "base_stat": 140
            },
            {
                "name": "special-attack",
                "base_stat": 60
            },
            {
                "name": "special-defense",
                "base_stat": 60
            },
            {
                "name": "speed",
                "base_stat": 40
            }
        ],
        "types": [
            {
                "name": "bug"
            },
            {
                "name": "steel"
            }
        ]
    },
    "dunsparce": {
        "id": 206,
        "name": "dunsparce",
        "height": 15,
        "weight": 140,
        "xp": 145,
        "image_url": "https://pokeres.bastionbot.org/images/pokemon/206.png",
        "abilities": [
            {
                "name": "serene-grace",
                "is_hidden": false
            },
            {
                "name": "run-away",
                "is_hidden": false
            },
            {
                "name": "rattled",
                "is_hidden": true
            }
        ],
        "stats": [
            {
                "name": "hp",
                "base_stat": 100
            },
            {
                "name": "attack",
                "base_stat": 70
            },
            {
                "name": "defense",
                "base_stat": 70
            },
            {
                "name": "special-attack",
                "base_stat": 65
            },
            {
                "name": "special-defense",
                "base_stat": 65
            },
            {
                "name": "speed",
                "base_stat": 45
            }
        ],
        "types": [
            {
                "name": "normal"
            }
        ]
    },
    "gligar": {
        "id": 207,
        "name": "gligar",
        "height": 11,
        "weight": 648,
        "xp": 86,
        "image_url": "https://pokeres.bastionbot.org/images/pokemon/207.png",
        "abilities": [
            {
                "name": "hyper-cutter",
                "is_hidden": false
            },
            {
                "name": "sand-veil",
                "is_hidden": false
            },
            {
                "name": "immunity",
                "is_hidden": true
            }
        ],
        "stats": [
            {
                "name": "hp",
                "base_stat": 65
            },
            {
                "name": "attack",
                "base_stat": 75
            },
            {
                "name": "defense",
                "base_stat": 105
            },
            {
                "name": "special-attack",
                "base_stat": 35
            },
            {
                "name": "special-defense",
                "base_stat": 65
            },
            {
                "name": "speed",
                "base_stat": 85
            }
        ],
        "types": [
            {
                "name": "ground"
            },
            {
                "name": "flying"
            }
        ]
    },
    "steelix": {
        "id": 208,
        "name": "steelix",
        "height": 92,
        "weight": 4000,
        "xp": 179,
        "image_url": "https://pokeres.bastionbot.org/images/pokemon/208.png",
        "abilities": [
            {
                "name": "rock-head",
                "is_hidden": false
            },
            {
                "name": "sturdy",
                "is_hidden": false
            },
            {
                "name": "sheer-force",
                "is_hidden": true
            }
        ],
        "stats": [
            {
                "name": "hp",
                "base_stat": 75
            },
            {
                "name": "attack",
                "base_stat": 85
            },
            {
                "name": "defense",
                "base_stat": 200
            },
            {
                "name": "special-attack",
                "base_stat": 55
            },
            {
                "name": "special-defense",
                "base_stat": 65
            },
            {
                "name": "speed",
                "base_stat": 30
            }
        ],
        "types": [
            {
                "name": "steel"
            },
            {
                "name": "ground"
            }
        ]
    },
    "snubbull": {
        "id": 209,
        "name": "snubbull",
        "height": 6,
        "weight": 78,
        "xp": 60,
        "image_url": "https://pokeres.bastionbot.org/images/pokemon/209.png",
        "abilities": [
            {
                "name": "intimidate",
                "is_hidden": false
            },
            {
                "name": "run-away",
                "is_hidden": false
            },
            {
                "name": "rattled",
                "is_hidden": true
            }
        ],
        "stats": [
            {
                "name": "hp",
                "base_stat": 60
            },
            {
                "name": "attack",
                "base_stat": 80
            },
            {
                "name": "defense",
                "base_stat": 50
            },
            {
                "name": "special-attack",
                "base_stat": 40
            },
            {
                "name": "special-defense",
                "base_stat": 40
            },
            {
                "name": "speed",
                "base_stat": 30
            }
        ],
        "types": [
            {
                "name": "fairy"
            }
        ]
    },
    "granbull": {
        "id": 210,
        "name": "granbull",
        "height": 14,
        "weight": 487,
        "xp": 158,
        "image_url": "https://pokeres.bastionbot.org/images/pokemon/210.png",
        "abilities": [
            {
                "name": "intimidate",
                "is_hidden": false
            },
            {
                "name": "quick-feet",
                "is_hidden": false
            },
            {
                "name": "rattled",
                "is_hidden": true
            }
        ],
        "stats": [
            {
                "name": "hp",
                "base_stat": 90
            },
            {
                "name": "attack",
                "base_stat": 120
            },
            {
                "name": "defense",
                "base_stat": 75
            },
            {
                "name": "special-attack",
                "base_stat": 60
            },
            {
                "name": "special-defense",
                "base_stat": 60
            },
            {
                "name": "speed",
                "base_stat": 45
            }
        ],
        "types": [
            {
                "name": "fairy"
            }
        ]
    },
    "qwilfish": {
        "id": 211,
        "name": "qwilfish",
        "height": 5,
        "weight": 39,
        "xp": 88,
        "image_url": "https://pokeres.bastionbot.org/images/pokemon/211.png",
        "abilities": [
            {
                "name": "poison-point",
                "is_hidden": false
            },
            {
                "name": "swift-swim",
                "is_hidden": false
            },
            {
                "name": "intimidate",
                "is_hidden": true
            }
        ],
        "stats": [
            {
                "name": "hp",
                "base_stat": 65
            },
            {
                "name": "attack",
                "base_stat": 95
            },
            {
                "name": "defense",
                "base_stat": 85
            },
            {
                "name": "special-attack",
                "base_stat": 55
            },
            {
                "name": "special-defense",
                "base_stat": 55
            },
            {
                "name": "speed",
                "base_stat": 85
            }
        ],
        "types": [
            {
                "name": "water"
            },
            {
                "name": "poison"
            }
        ]
    },
    "scizor": {
        "id": 212,
        "name": "scizor",
        "height": 18,
        "weight": 1180,
        "xp": 175,
        "image_url": "https://pokeres.bastionbot.org/images/pokemon/212.png",
        "abilities": [
            {
                "name": "swarm",
                "is_hidden": false
            },
            {
                "name": "technician",
                "is_hidden": false
            },
            {
                "name": "light-metal",
                "is_hidden": true
            }
        ],
        "stats": [
            {
                "name": "hp",
                "base_stat": 70
            },
            {
                "name": "attack",
                "base_stat": 130
            },
            {
                "name": "defense",
                "base_stat": 100
            },
            {
                "name": "special-attack",
                "base_stat": 55
            },
            {
                "name": "special-defense",
                "base_stat": 80
            },
            {
                "name": "speed",
                "base_stat": 65
            }
        ],
        "types": [
            {
                "name": "bug"
            },
            {
                "name": "steel"
            }
        ]
    },
    "shuckle": {
        "id": 213,
        "name": "shuckle",
        "height": 6,
        "weight": 205,
        "xp": 177,
        "image_url": "https://pokeres.bastionbot.org/images/pokemon/213.png",
        "abilities": [
            {
                "name": "sturdy",
                "is_hidden": false
            },
            {
                "name": "gluttony",
                "is_hidden": false
            },
            {
                "name": "contrary",
                "is_hidden": true
            }
        ],
        "stats": [
            {
                "name": "hp",
                "base_stat": 20
            },
            {
                "name": "attack",
                "base_stat": 10
            },
            {
                "name": "defense",
                "base_stat": 230
            },
            {
                "name": "special-attack",
                "base_stat": 10
            },
            {
                "name": "special-defense",
                "base_stat": 230
            },
            {
                "name": "speed",
                "base_stat": 5
            }
        ],
        "types": [
            {
                "name": "bug"
            },
            {
                "name": "rock"
            }
        ]
    },
    "heracross": {
        "id": 214,
        "name": "heracross",
        "height": 15,
        "weight": 540,
        "xp": 175,
        "image_url": "https://pokeres.bastionbot.org/images/pokemon/214.png",
        "abilities": [
            {
                "name": "swarm",
                "is_hidden": false
            },
            {
                "name": "guts",
                "is_hidden": false
            },
            {
                "name": "moxie",
                "is_hidden": true
            }
        ],
        "stats": [
            {
                "name": "hp",
                "base_stat": 80
            },
            {
                "name": "attack",
                "base_stat": 125
            },
            {
                "name": "defense",
                "base_stat": 75
            },
            {
                "name": "special-attack",
                "base_stat": 40
            },
            {
                "name": "special-defense",
                "base_stat": 95
            },
            {
                "name": "speed",
                "base_stat": 85
            }
        ],
        "types": [
            {
                "name": "bug"
            },
            {
                "name": "fighting"
            }
        ]
    },
    "sneasel": {
        "id": 215,
        "name": "sneasel",
        "height": 9,
        "weight": 280,
        "xp": 86,
        "image_url": "https://pokeres.bastionbot.org/images/pokemon/215.png",
        "abilities": [
            {
                "name": "inner-focus",
                "is_hidden": false
            },
            {
                "name": "keen-eye",
                "is_hidden": false
            },
            {
                "name": "pickpocket",
                "is_hidden": true
            }
        ],
        "stats": [
            {
                "name": "hp",
                "base_stat": 55
            },
            {
                "name": "attack",
                "base_stat": 95
            },
            {
                "name": "defense",
                "base_stat": 55
            },
            {
                "name": "special-attack",
                "base_stat": 35
            },
            {
                "name": "special-defense",
                "base_stat": 75
            },
            {
                "name": "speed",
                "base_stat": 115
            }
        ],
        "types": [
            {
                "name": "dark"
            },
            {
                "name": "ice"
            }
        ]
    },
    "teddiursa": {
        "id": 216,
        "name": "teddiursa",
        "height": 6,
        "weight": 88,
        "xp": 66,
        "image_url": "https://pokeres.bastionbot.org/images/pokemon/216.png",
        "abilities": [
            {
                "name": "pickup",
                "is_hidden": false
            },
            {
                "name": "quick-feet",
                "is_hidden": false
            },
            {
                "name": "honey-gather",
                "is_hidden": true
            }
        ],
        "stats": [
            {
                "name": "hp",
                "base_stat": 60
            },
            {
                "name": "attack",
                "base_stat": 80
            },
            {
                "name": "defense",
                "base_stat": 50
            },
            {
                "name": "special-attack",
                "base_stat": 50
            },
            {
                "name": "special-defense",
                "base_stat": 50
            },
            {
                "name": "speed",
                "base_stat": 40
            }
        ],
        "types": [
            {
                "name": "normal"
            }
        ]
    },
    "ursaring": {
        "id": 217,
        "name": "ursaring",
        "height": 18,
        "weight": 1258,
        "xp": 175,
        "image_url": "https://pokeres.bastionbot.org/images/pokemon/217.png",
        "abilities": [
            {
                "name": "guts",
                "is_hidden": false
            },
            {
                "name": "quick-feet",
                "is_hidden": false
            },
            {
                "name": "unnerve",
                "is_hidden": true
            }
        ],
        "stats": [
            {
                "name": "hp",
                "base_stat": 90
            },
            {
                "name": "attack",
                "base_stat": 130
            },
            {
                "name": "defense",
                "base_stat": 75
            },
            {
                "name": "special-attack",
                "base_stat": 75
            },
            {
                "name": "special-defense",
                "base_stat": 75
            },
            {
                "name": "speed",
                "base_stat": 55
            }
        ],
        "types": [
            {
                "name": "normal"
            }
        ]
    },
    "slugma": {
        "id": 218,
        "name": "slugma",
        "height": 7,
        "weight": 350,
        "xp": 50,
        "image_url": "https://pokeres.bastionbot.org/images/pokemon/218.png",
        "abilities": [
            {
                "name": "magma-armor",
                "is_hidden": false
            },
            {
                "name": "flame-body",
                "is_hidden": false
            },
            {
                "name": "weak-armor",
                "is_hidden": true
            }
        ],
        "stats": [
            {
                "name": "hp",
                "base_stat": 40
            },
            {
                "name": "attack",
                "base_stat": 40
            },
            {
                "name": "defense",
                "base_stat": 40
            },
            {
                "name": "special-attack",
                "base_stat": 70
            },
            {
                "name": "special-defense",
                "base_stat": 40
            },
            {
                "name": "speed",
                "base_stat": 20
            }
        ],
        "types": [
            {
                "name": "fire"
            }
        ]
    },
    "magcargo": {
        "id": 219,
        "name": "magcargo",
        "height": 8,
        "weight": 550,
        "xp": 151,
        "image_url": "https://pokeres.bastionbot.org/images/pokemon/219.png",
        "abilities": [
            {
                "name": "magma-armor",
                "is_hidden": false
            },
            {
                "name": "flame-body",
                "is_hidden": false
            },
            {
                "name": "weak-armor",
                "is_hidden": true
            }
        ],
        "stats": [
            {
                "name": "hp",
                "base_stat": 60
            },
            {
                "name": "attack",
                "base_stat": 50
            },
            {
                "name": "defense",
                "base_stat": 120
            },
            {
                "name": "special-attack",
                "base_stat": 90
            },
            {
                "name": "special-defense",
                "base_stat": 80
            },
            {
                "name": "speed",
                "base_stat": 30
            }
        ],
        "types": [
            {
                "name": "fire"
            },
            {
                "name": "rock"
            }
        ]
    },
    "swinub": {
        "id": 220,
        "name": "swinub",
        "height": 4,
        "weight": 65,
        "xp": 50,
        "image_url": "https://pokeres.bastionbot.org/images/pokemon/220.png",
        "abilities": [
            {
                "name": "oblivious",
                "is_hidden": false
            },
            {
                "name": "snow-cloak",
                "is_hidden": false
            },
            {
                "name": "thick-fat",
                "is_hidden": true
            }
        ],
        "stats": [
            {
                "name": "hp",
                "base_stat": 50
            },
            {
                "name": "attack",
                "base_stat": 50
            },
            {
                "name": "defense",
                "base_stat": 40
            },
            {
                "name": "special-attack",
                "base_stat": 30
            },
            {
                "name": "special-defense",
                "base_stat": 30
            },
            {
                "name": "speed",
                "base_stat": 50
            }
        ],
        "types": [
            {
                "name": "ice"
            },
            {
                "name": "ground"
            }
        ]
    },
    "piloswine": {
        "id": 221,
        "name": "piloswine",
        "height": 11,
        "weight": 558,
        "xp": 158,
        "image_url": "https://pokeres.bastionbot.org/images/pokemon/221.png",
        "abilities": [
            {
                "name": "oblivious",
                "is_hidden": false
            },
            {
                "name": "snow-cloak",
                "is_hidden": false
            },
            {
                "name": "thick-fat",
                "is_hidden": true
            }
        ],
        "stats": [
            {
                "name": "hp",
                "base_stat": 100
            },
            {
                "name": "attack",
                "base_stat": 100
            },
            {
                "name": "defense",
                "base_stat": 80
            },
            {
                "name": "special-attack",
                "base_stat": 60
            },
            {
                "name": "special-defense",
                "base_stat": 60
            },
            {
                "name": "speed",
                "base_stat": 50
            }
        ],
        "types": [
            {
                "name": "ice"
            },
            {
                "name": "ground"
            }
        ]
    },
    "corsola": {
        "id": 222,
        "name": "corsola",
        "height": 6,
        "weight": 50,
        "xp": 144,
        "image_url": "https://pokeres.bastionbot.org/images/pokemon/222.png",
        "abilities": [
            {
                "name": "hustle",
                "is_hidden": false
            },
            {
                "name": "natural-cure",
                "is_hidden": false
            },
            {
                "name": "regenerator",
                "is_hidden": true
            }
        ],
        "stats": [
            {
                "name": "hp",
                "base_stat": 65
            },
            {
                "name": "attack",
                "base_stat": 55
            },
            {
                "name": "defense",
                "base_stat": 95
            },
            {
                "name": "special-attack",
                "base_stat": 65
            },
            {
                "name": "special-defense",
                "base_stat": 95
            },
            {
                "name": "speed",
                "base_stat": 35
            }
        ],
        "types": [
            {
                "name": "water"
            },
            {
                "name": "rock"
            }
        ]
    },
    "remoraid": {
        "id": 223,
        "name": "remoraid",
        "height": 6,
        "weight": 120,
        "xp": 60,
        "image_url": "https://pokeres.bastionbot.org/images/pokemon/223.png",
        "abilities": [
            {
                "name": "hustle",
                "is_hidden": false
            },
            {
                "name": "sniper",
                "is_hidden": false
            },
            {
                "name": "moody",
                "is_hidden": true
            }
        ],
        "stats": [
            {
                "name": "hp",
                "base_stat": 35
            },
            {
                "name": "attack",
                "base_stat": 65
            },
            {
                "name": "defense",
                "base_stat": 35
            },
            {
                "name": "special-attack",
                "base_stat": 65
            },
            {
                "name": "special-defense",
                "base_stat": 35
            },
            {
                "name": "speed",
                "base_stat": 65
            }
        ],
        "types": [
            {
                "name": "water"
            }
        ]
    },
    "octillery": {
        "id": 224,
        "name": "octillery",
        "height": 9,
        "weight": 285,
        "xp": 168,
        "image_url": "https://pokeres.bastionbot.org/images/pokemon/224.png",
        "abilities": [
            {
                "name": "suction-cups",
                "is_hidden": false
            },
            {
                "name": "sniper",
                "is_hidden": false
            },
            {
                "name": "moody",
                "is_hidden": true
            }
        ],
        "stats": [
            {
                "name": "hp",
                "base_stat": 75
            },
            {
                "name": "attack",
                "base_stat": 105
            },
            {
                "name": "defense",
                "base_stat": 75
            },
            {
                "name": "special-attack",
                "base_stat": 105
            },
            {
                "name": "special-defense",
                "base_stat": 75
            },
            {
                "name": "speed",
                "base_stat": 45
            }
        ],
        "types": [
            {
                "name": "water"
            }
        ]
    },
    "delibird": {
        "id": 225,
        "name": "delibird",
        "height": 9,
        "weight": 160,
        "xp": 116,
        "image_url": "https://pokeres.bastionbot.org/images/pokemon/225.png",
        "abilities": [
            {
                "name": "vital-spirit",
                "is_hidden": false
            },
            {
                "name": "hustle",
                "is_hidden": false
            },
            {
                "name": "insomnia",
                "is_hidden": true
            }
        ],
        "stats": [
            {
                "name": "hp",
                "base_stat": 45
            },
            {
                "name": "attack",
                "base_stat": 55
            },
            {
                "name": "defense",
                "base_stat": 45
            },
            {
                "name": "special-attack",
                "base_stat": 65
            },
            {
                "name": "special-defense",
                "base_stat": 45
            },
            {
                "name": "speed",
                "base_stat": 75
            }
        ],
        "types": [
            {
                "name": "ice"
            },
            {
                "name": "flying"
            }
        ]
    },
    "mantine": {
        "id": 226,
        "name": "mantine",
        "height": 21,
        "weight": 2200,
        "xp": 170,
        "image_url": "https://pokeres.bastionbot.org/images/pokemon/226.png",
        "abilities": [
            {
                "name": "swift-swim",
                "is_hidden": false
            },
            {
                "name": "water-absorb",
                "is_hidden": false
            },
            {
                "name": "water-veil",
                "is_hidden": true
            }
        ],
        "stats": [
            {
                "name": "hp",
                "base_stat": 85
            },
            {
                "name": "attack",
                "base_stat": 40
            },
            {
                "name": "defense",
                "base_stat": 70
            },
            {
                "name": "special-attack",
                "base_stat": 80
            },
            {
                "name": "special-defense",
                "base_stat": 140
            },
            {
                "name": "speed",
                "base_stat": 70
            }
        ],
        "types": [
            {
                "name": "water"
            },
            {
                "name": "flying"
            }
        ]
    },
    "skarmory": {
        "id": 227,
        "name": "skarmory",
        "height": 17,
        "weight": 505,
        "xp": 163,
        "image_url": "https://pokeres.bastionbot.org/images/pokemon/227.png",
        "abilities": [
            {
                "name": "keen-eye",
                "is_hidden": false
            },
            {
                "name": "sturdy",
                "is_hidden": false
            },
            {
                "name": "weak-armor",
                "is_hidden": true
            }
        ],
        "stats": [
            {
                "name": "hp",
                "base_stat": 65
            },
            {
                "name": "attack",
                "base_stat": 80
            },
            {
                "name": "defense",
                "base_stat": 140
            },
            {
                "name": "special-attack",
                "base_stat": 40
            },
            {
                "name": "special-defense",
                "base_stat": 70
            },
            {
                "name": "speed",
                "base_stat": 70
            }
        ],
        "types": [
            {
                "name": "steel"
            },
            {
                "name": "flying"
            }
        ]
    },
    "houndour": {
        "id": 228,
        "name": "houndour",
        "height": 6,
        "weight": 108,
        "xp": 66,
        "image_url": "https://pokeres.bastionbot.org/images/pokemon/228.png",
        "abilities": [
            {
                "name": "early-bird",
                "is_hidden": false
            },
            {
                "name": "flash-fire",
                "is_hidden": false
            },
            {
                "name": "unnerve",
                "is_hidden": true
            }
        ],
        "stats": [
            {
                "name": "hp",
                "base_stat": 45
            },
            {
                "name": "attack",
                "base_stat": 60
            },
            {
                "name": "defense",
                "base_stat": 30
            },
            {
                "name": "special-attack",
                "base_stat": 80
            },
            {
                "name": "special-defense",
                "base_stat": 50
            },
            {
                "name": "speed",
                "base_stat": 65
            }
        ],
        "types": [
            {
                "name": "dark"
            },
            {
                "name": "fire"
            }
        ]
    },
    "houndoom": {
        "id": 229,
        "name": "houndoom",
        "height": 14,
        "weight": 350,
        "xp": 175,
        "image_url": "https://pokeres.bastionbot.org/images/pokemon/229.png",
        "abilities": [
            {
                "name": "early-bird",
                "is_hidden": false
            },
            {
                "name": "flash-fire",
                "is_hidden": false
            },
            {
                "name": "unnerve",
                "is_hidden": true
            }
        ],
        "stats": [
            {
                "name": "hp",
                "base_stat": 75
            },
            {
                "name": "attack",
                "base_stat": 90
            },
            {
                "name": "defense",
                "base_stat": 50
            },
            {
                "name": "special-attack",
                "base_stat": 110
            },
            {
                "name": "special-defense",
                "base_stat": 80
            },
            {
                "name": "speed",
                "base_stat": 95
            }
        ],
        "types": [
            {
                "name": "dark"
            },
            {
                "name": "fire"
            }
        ]
    },
    "kingdra": {
        "id": 230,
        "name": "kingdra",
        "height": 18,
        "weight": 1520,
        "xp": 243,
        "image_url": "https://pokeres.bastionbot.org/images/pokemon/230.png",
        "abilities": [
            {
                "name": "swift-swim",
                "is_hidden": false
            },
            {
                "name": "sniper",
                "is_hidden": false
            },
            {
                "name": "damp",
                "is_hidden": true
            }
        ],
        "stats": [
            {
                "name": "hp",
                "base_stat": 75
            },
            {
                "name": "attack",
                "base_stat": 95
            },
            {
                "name": "defense",
                "base_stat": 95
            },
            {
                "name": "special-attack",
                "base_stat": 95
            },
            {
                "name": "special-defense",
                "base_stat": 95
            },
            {
                "name": "speed",
                "base_stat": 85
            }
        ],
        "types": [
            {
                "name": "water"
            },
            {
                "name": "dragon"
            }
        ]
    },
    "phanpy": {
        "id": 231,
        "name": "phanpy",
        "height": 5,
        "weight": 335,
        "xp": 66,
        "image_url": "https://pokeres.bastionbot.org/images/pokemon/231.png",
        "abilities": [
            {
                "name": "pickup",
                "is_hidden": false
            },
            {
                "name": "sand-veil",
                "is_hidden": true
            }
        ],
        "stats": [
            {
                "name": "hp",
                "base_stat": 90
            },
            {
                "name": "attack",
                "base_stat": 60
            },
            {
                "name": "defense",
                "base_stat": 60
            },
            {
                "name": "special-attack",
                "base_stat": 40
            },
            {
                "name": "special-defense",
                "base_stat": 40
            },
            {
                "name": "speed",
                "base_stat": 40
            }
        ],
        "types": [
            {
                "name": "ground"
            }
        ]
    },
    "donphan": {
        "id": 232,
        "name": "donphan",
        "height": 11,
        "weight": 1200,
        "xp": 175,
        "image_url": "https://pokeres.bastionbot.org/images/pokemon/232.png",
        "abilities": [
            {
                "name": "sturdy",
                "is_hidden": false
            },
            {
                "name": "sand-veil",
                "is_hidden": true
            }
        ],
        "stats": [
            {
                "name": "hp",
                "base_stat": 90
            },
            {
                "name": "attack",
                "base_stat": 120
            },
            {
                "name": "defense",
                "base_stat": 120
            },
            {
                "name": "special-attack",
                "base_stat": 60
            },
            {
                "name": "special-defense",
                "base_stat": 60
            },
            {
                "name": "speed",
                "base_stat": 50
            }
        ],
        "types": [
            {
                "name": "ground"
            }
        ]
    },
    "porygon2": {
        "id": 233,
        "name": "porygon2",
        "height": 6,
        "weight": 325,
        "xp": 180,
        "image_url": "https://pokeres.bastionbot.org/images/pokemon/233.png",
        "abilities": [
            {
                "name": "trace",
                "is_hidden": false
            },
            {
                "name": "download",
                "is_hidden": false
            },
            {
                "name": "analytic",
                "is_hidden": true
            }
        ],
        "stats": [
            {
                "name": "hp",
                "base_stat": 85
            },
            {
                "name": "attack",
                "base_stat": 80
            },
            {
                "name": "defense",
                "base_stat": 90
            },
            {
                "name": "special-attack",
                "base_stat": 105
            },
            {
                "name": "special-defense",
                "base_stat": 95
            },
            {
                "name": "speed",
                "base_stat": 60
            }
        ],
        "types": [
            {
                "name": "normal"
            }
        ]
    },
    "stantler": {
        "id": 234,
        "name": "stantler",
        "height": 14,
        "weight": 712,
        "xp": 163,
        "image_url": "https://pokeres.bastionbot.org/images/pokemon/234.png",
        "abilities": [
            {
                "name": "intimidate",
                "is_hidden": false
            },
            {
                "name": "frisk",
                "is_hidden": false
            },
            {
                "name": "sap-sipper",
                "is_hidden": true
            }
        ],
        "stats": [
            {
                "name": "hp",
                "base_stat": 73
            },
            {
                "name": "attack",
                "base_stat": 95
            },
            {
                "name": "defense",
                "base_stat": 62
            },
            {
                "name": "special-attack",
                "base_stat": 85
            },
            {
                "name": "special-defense",
                "base_stat": 65
            },
            {
                "name": "speed",
                "base_stat": 85
            }
        ],
        "types": [
            {
                "name": "normal"
            }
        ]
    },
    "smeargle": {
        "id": 235,
        "name": "smeargle",
        "height": 12,
        "weight": 580,
        "xp": 88,
        "image_url": "https://pokeres.bastionbot.org/images/pokemon/235.png",
        "abilities": [
            {
                "name": "own-tempo",
                "is_hidden": false
            },
            {
                "name": "technician",
                "is_hidden": false
            },
            {
                "name": "moody",
                "is_hidden": true
            }
        ],
        "stats": [
            {
                "name": "hp",
                "base_stat": 55
            },
            {
                "name": "attack",
                "base_stat": 20
            },
            {
                "name": "defense",
                "base_stat": 35
            },
            {
                "name": "special-attack",
                "base_stat": 20
            },
            {
                "name": "special-defense",
                "base_stat": 45
            },
            {
                "name": "speed",
                "base_stat": 75
            }
        ],
        "types": [
            {
                "name": "normal"
            }
        ]
    },
    "tyrogue": {
        "id": 236,
        "name": "tyrogue",
        "height": 7,
        "weight": 210,
        "xp": 42,
        "image_url": "https://pokeres.bastionbot.org/images/pokemon/236.png",
        "abilities": [
            {
                "name": "guts",
                "is_hidden": false
            },
            {
                "name": "steadfast",
                "is_hidden": false
            },
            {
                "name": "vital-spirit",
                "is_hidden": true
            }
        ],
        "stats": [
            {
                "name": "hp",
                "base_stat": 35
            },
            {
                "name": "attack",
                "base_stat": 35
            },
            {
                "name": "defense",
                "base_stat": 35
            },
            {
                "name": "special-attack",
                "base_stat": 35
            },
            {
                "name": "special-defense",
                "base_stat": 35
            },
            {
                "name": "speed",
                "base_stat": 35
            }
        ],
        "types": [
            {
                "name": "fighting"
            }
        ]
    },
    "hitmontop": {
        "id": 237,
        "name": "hitmontop",
        "height": 14,
        "weight": 480,
        "xp": 159,
        "image_url": "https://pokeres.bastionbot.org/images/pokemon/237.png",
        "abilities": [
            {
                "name": "intimidate",
                "is_hidden": false
            },
            {
                "name": "technician",
                "is_hidden": false
            },
            {
                "name": "steadfast",
                "is_hidden": true
            }
        ],
        "stats": [
            {
                "name": "hp",
                "base_stat": 50
            },
            {
                "name": "attack",
                "base_stat": 95
            },
            {
                "name": "defense",
                "base_stat": 95
            },
            {
                "name": "special-attack",
                "base_stat": 35
            },
            {
                "name": "special-defense",
                "base_stat": 110
            },
            {
                "name": "speed",
                "base_stat": 70
            }
        ],
        "types": [
            {
                "name": "fighting"
            }
        ]
    },
    "smoochum": {
        "id": 238,
        "name": "smoochum",
        "height": 4,
        "weight": 60,
        "xp": 61,
        "image_url": "https://pokeres.bastionbot.org/images/pokemon/238.png",
        "abilities": [
            {
                "name": "oblivious",
                "is_hidden": false
            },
            {
                "name": "forewarn",
                "is_hidden": false
            },
            {
                "name": "hydration",
                "is_hidden": true
            }
        ],
        "stats": [
            {
                "name": "hp",
                "base_stat": 45
            },
            {
                "name": "attack",
                "base_stat": 30
            },
            {
                "name": "defense",
                "base_stat": 15
            },
            {
                "name": "special-attack",
                "base_stat": 85
            },
            {
                "name": "special-defense",
                "base_stat": 65
            },
            {
                "name": "speed",
                "base_stat": 65
            }
        ],
        "types": [
            {
                "name": "ice"
            },
            {
                "name": "psychic"
            }
        ]
    },
    "elekid": {
        "id": 239,
        "name": "elekid",
        "height": 6,
        "weight": 235,
        "xp": 72,
        "image_url": "https://pokeres.bastionbot.org/images/pokemon/239.png",
        "abilities": [
            {
                "name": "static",
                "is_hidden": false
            },
            {
                "name": "vital-spirit",
                "is_hidden": true
            }
        ],
        "stats": [
            {
                "name": "hp",
                "base_stat": 45
            },
            {
                "name": "attack",
                "base_stat": 63
            },
            {
                "name": "defense",
                "base_stat": 37
            },
            {
                "name": "special-attack",
                "base_stat": 65
            },
            {
                "name": "special-defense",
                "base_stat": 55
            },
            {
                "name": "speed",
                "base_stat": 95
            }
        ],
        "types": [
            {
                "name": "electric"
            }
        ]
    },
    "magby": {
        "id": 240,
        "name": "magby",
        "height": 7,
        "weight": 214,
        "xp": 73,
        "image_url": "https://pokeres.bastionbot.org/images/pokemon/240.png",
        "abilities": [
            {
                "name": "flame-body",
                "is_hidden": false
            },
            {
                "name": "vital-spirit",
                "is_hidden": true
            }
        ],
        "stats": [
            {
                "name": "hp",
                "base_stat": 45
            },
            {
                "name": "attack",
                "base_stat": 75
            },
            {
                "name": "defense",
                "base_stat": 37
            },
            {
                "name": "special-attack",
                "base_stat": 70
            },
            {
                "name": "special-defense",
                "base_stat": 55
            },
            {
                "name": "speed",
                "base_stat": 83
            }
        ],
        "types": [
            {
                "name": "fire"
            }
        ]
    },
    "miltank": {
        "id": 241,
        "name": "miltank",
        "height": 12,
        "weight": 755,
        "xp": 172,
        "image_url": "https://pokeres.bastionbot.org/images/pokemon/241.png",
        "abilities": [
            {
                "name": "thick-fat",
                "is_hidden": false
            },
            {
                "name": "scrappy",
                "is_hidden": false
            },
            {
                "name": "sap-sipper",
                "is_hidden": true
            }
        ],
        "stats": [
            {
                "name": "hp",
                "base_stat": 95
            },
            {
                "name": "attack",
                "base_stat": 80
            },
            {
                "name": "defense",
                "base_stat": 105
            },
            {
                "name": "special-attack",
                "base_stat": 40
            },
            {
                "name": "special-defense",
                "base_stat": 70
            },
            {
                "name": "speed",
                "base_stat": 100
            }
        ],
        "types": [
            {
                "name": "normal"
            }
        ]
    },
    "blissey": {
        "id": 242,
        "name": "blissey",
        "height": 15,
        "weight": 468,
        "xp": 608,
        "image_url": "https://pokeres.bastionbot.org/images/pokemon/242.png",
        "abilities": [
            {
                "name": "natural-cure",
                "is_hidden": false
            },
            {
                "name": "serene-grace",
                "is_hidden": false
            },
            {
                "name": "healer",
                "is_hidden": true
            }
        ],
        "stats": [
            {
                "name": "hp",
                "base_stat": 255
            },
            {
                "name": "attack",
                "base_stat": 10
            },
            {
                "name": "defense",
                "base_stat": 10
            },
            {
                "name": "special-attack",
                "base_stat": 75
            },
            {
                "name": "special-defense",
                "base_stat": 135
            },
            {
                "name": "speed",
                "base_stat": 55
            }
        ],
        "types": [
            {
                "name": "normal"
            }
        ]
    },
    "raikou": {
        "id": 243,
        "name": "raikou",
        "height": 19,
        "weight": 1780,
        "xp": 261,
        "image_url": "https://pokeres.bastionbot.org/images/pokemon/243.png",
        "abilities": [
            {
                "name": "pressure",
                "is_hidden": false
            },
            {
                "name": "inner-focus",
                "is_hidden": true
            }
        ],
        "stats": [
            {
                "name": "hp",
                "base_stat": 90
            },
            {
                "name": "attack",
                "base_stat": 85
            },
            {
                "name": "defense",
                "base_stat": 75
            },
            {
                "name": "special-attack",
                "base_stat": 115
            },
            {
                "name": "special-defense",
                "base_stat": 100
            },
            {
                "name": "speed",
                "base_stat": 115
            }
        ],
        "types": [
            {
                "name": "electric"
            }
        ]
    },
    "entei": {
        "id": 244,
        "name": "entei",
        "height": 21,
        "weight": 1980,
        "xp": 261,
        "image_url": "https://pokeres.bastionbot.org/images/pokemon/244.png",
        "abilities": [
            {
                "name": "pressure",
                "is_hidden": false
            },
            {
                "name": "inner-focus",
                "is_hidden": true
            }
        ],
        "stats": [
            {
                "name": "hp",
                "base_stat": 115
            },
            {
                "name": "attack",
                "base_stat": 115
            },
            {
                "name": "defense",
                "base_stat": 85
            },
            {
                "name": "special-attack",
                "base_stat": 90
            },
            {
                "name": "special-defense",
                "base_stat": 75
            },
            {
                "name": "speed",
                "base_stat": 100
            }
        ],
        "types": [
            {
                "name": "fire"
            }
        ]
    },
    "suicune": {
        "id": 245,
        "name": "suicune",
        "height": 20,
        "weight": 1870,
        "xp": 261,
        "image_url": "https://pokeres.bastionbot.org/images/pokemon/245.png",
        "abilities": [
            {
                "name": "pressure",
                "is_hidden": false
            },
            {
                "name": "inner-focus",
                "is_hidden": true
            }
        ],
        "stats": [
            {
                "name": "hp",
                "base_stat": 100
            },
            {
                "name": "attack",
                "base_stat": 75
            },
            {
                "name": "defense",
                "base_stat": 115
            },
            {
                "name": "special-attack",
                "base_stat": 90
            },
            {
                "name": "special-defense",
                "base_stat": 115
            },
            {
                "name": "speed",
                "base_stat": 85
            }
        ],
        "types": [
            {
                "name": "water"
            }
        ]
    },
    "larvitar": {
        "id": 246,
        "name": "larvitar",
        "height": 6,
        "weight": 720,
        "xp": 60,
        "image_url": "https://pokeres.bastionbot.org/images/pokemon/246.png",
        "abilities": [
            {
                "name": "guts",
                "is_hidden": false
            },
            {
                "name": "sand-veil",
                "is_hidden": true
            }
        ],
        "stats": [
            {
                "name": "hp",
                "base_stat": 50
            },
            {
                "name": "attack",
                "base_stat": 64
            },
            {
                "name": "defense",
                "base_stat": 50
            },
            {
                "name": "special-attack",
                "base_stat": 45
            },
            {
                "name": "special-defense",
                "base_stat": 50
            },
            {
                "name": "speed",
                "base_stat": 41
            }
        ],
        "types": [
            {
                "name": "rock"
            },
            {
                "name": "ground"
            }
        ]
    },
    "pupitar": {
        "id": 247,
        "name": "pupitar",
        "height": 12,
        "weight": 1520,
        "xp": 144,
        "image_url": "https://pokeres.bastionbot.org/images/pokemon/247.png",
        "abilities": [
            {
                "name": "shed-skin",
                "is_hidden": false
            }
        ],
        "stats": [
            {
                "name": "hp",
                "base_stat": 70
            },
            {
                "name": "attack",
                "base_stat": 84
            },
            {
                "name": "defense",
                "base_stat": 70
            },
            {
                "name": "special-attack",
                "base_stat": 65
            },
            {
                "name": "special-defense",
                "base_stat": 70
            },
            {
                "name": "speed",
                "base_stat": 51
            }
        ],
        "types": [
            {
                "name": "rock"
            },
            {
                "name": "ground"
            }
        ]
    },
    "tyranitar": {
        "id": 248,
        "name": "tyranitar",
        "height": 20,
        "weight": 2020,
        "xp": 270,
        "image_url": "https://pokeres.bastionbot.org/images/pokemon/248.png",
        "abilities": [
            {
                "name": "sand-stream",
                "is_hidden": false
            },
            {
                "name": "unnerve",
                "is_hidden": true
            }
        ],
        "stats": [
            {
                "name": "hp",
                "base_stat": 100
            },
            {
                "name": "attack",
                "base_stat": 134
            },
            {
                "name": "defense",
                "base_stat": 110
            },
            {
                "name": "special-attack",
                "base_stat": 95
            },
            {
                "name": "special-defense",
                "base_stat": 100
            },
            {
                "name": "speed",
                "base_stat": 61
            }
        ],
        "types": [
            {
                "name": "rock"
            },
            {
                "name": "dark"
            }
        ]
    },
    "lugia": {
        "id": 249,
        "name": "lugia",
        "height": 52,
        "weight": 2160,
        "xp": 306,
        "image_url": "https://pokeres.bastionbot.org/images/pokemon/249.png",
        "abilities": [
            {
                "name": "pressure",
                "is_hidden": false
            },
            {
                "name": "multiscale",
                "is_hidden": true
            }
        ],
        "stats": [
            {
                "name": "hp",
                "base_stat": 106
            },
            {
                "name": "attack",
                "base_stat": 90
            },
            {
                "name": "defense",
                "base_stat": 130
            },
            {
                "name": "special-attack",
                "base_stat": 90
            },
            {
                "name": "special-defense",
                "base_stat": 154
            },
            {
                "name": "speed",
                "base_stat": 110
            }
        ],
        "types": [
            {
                "name": "psychic"
            },
            {
                "name": "flying"
            }
        ]
    },
    "ho-oh": {
        "id": 250,
        "name": "ho-oh",
        "height": 38,
        "weight": 1990,
        "xp": 306,
        "image_url": "https://pokeres.bastionbot.org/images/pokemon/250.png",
        "abilities": [
            {
                "name": "pressure",
                "is_hidden": false
            },
            {
                "name": "regenerator",
                "is_hidden": true
            }
        ],
        "stats": [
            {
                "name": "hp",
                "base_stat": 106
            },
            {
                "name": "attack",
                "base_stat": 130
            },
            {
                "name": "defense",
                "base_stat": 90
            },
            {
                "name": "special-attack",
                "base_stat": 110
            },
            {
                "name": "special-defense",
                "base_stat": 154
            },
            {
                "name": "speed",
                "base_stat": 90
            }
        ],
        "types": [
            {
                "name": "fire"
            },
            {
                "name": "flying"
            }
        ]
    }
}